ptk/__init__.py
ptk/cli.py
ptk/gui.py
ptk/core/__init__.py
ptk/core/files.py
ptk/core/passgen.py
privacy_toolkit-0.0.3.dist-info/METADATA
privacy_toolkit-0.0.3.dist-info/WHEEL
privacy_toolkit-0.0.3.dist-info/entry_points.txt
privacy_toolkit-0.0.3.dist-info/licenses/LICENSE.txt
privacy_toolkit-0.0.3.dist-info/RECORD
